[
  {
    "title": "Introduction",
    "description": "What exactly are we doing here?",
    "path": "index",
    "content": "<script>\n\timport { Callout } from '@ldn-viz/ui'\n</script>\n<h1>Hello there!</h1>\n<callout>\nThis feature is still being worked on.\n</callout>",
    "raw": "<script>\n\timport { Callout } from '@ldn-viz/ui'\n</script>\n\n# Hello there!\n\n<Callout>\nThis feature is still being worked on.\n</Callout>",
    "toc": [
      {
        "title": "Hello there!",
        "url": "#hello-there",
        "items": []
      }
    ],
    "section": "Overview",
    "slug": "index",
    "slugFull": "/index"
  }
]